{
    "version": "0.1.0",
    "description": "Markdown viewer for the AI age",
    "homepage": "https://github.com/HonotaKobo/mdview",
    "license": "MIT",
    "architecture": {
        "64bit": {
            "url": "https://github.com/HonotaKobo/mdview/releases/download/v0.1.0/mdview_0.1.0_x64_en-US.msi",
            "hash": "b921a50a724cb269bacb8a7dfbf3510988558a543abe309437bfae828b0adb5d"
        }
    },
    "extract_dir": "mdview",
    "bin": "mdview.exe",
    "shortcuts": [
        ["mdview.exe", "mdview"]
    ]
}
